nati_log/__init__.py
nati_log/client.py
nati_log/middleware.py
natilog_lib-1.2.0.dist-info/METADATA
natilog_lib-1.2.0.dist-info/WHEEL
natilog_lib-1.2.0.dist-info/top_level.txt
natilog_lib-1.2.0.dist-info/RECORD
