Metadata-Version: 2.1
Name: natilog-lib
Version: 1.2.0
Summary: Librería para interactuar con la API de NatiLog
Home-page: UNKNOWN
Author: Natalí
Author-email: UNKNOWN
License: UNKNOWN
Platform: UNKNOWN
Requires-Dist: requests>=2.25.1
